Metadata-Version: 2.1
Name: djfuesah
Version: 1.0
Summary: a library for DS CAA Developer
Home-page: UNKNOWN
Author: linzhe
Author-email: geekluca@qq.com
License: MIT License
Keywords: ds caa
Platform: any
